{"cameraMode":{"drawMode":0,"name":"Shaded","section":"Shading Mode"},"sceneLighting":false,"audioPlay":false,"sceneViewState":{"m_AlwaysRefresh":false,"showFog":true,"showSkybox":false,"showFlares":true,"showImageEffects":true,"showParticleSystems":true,"showVisualEffectGraphs":true,"m_FxEnabled":true},"in2DMode":false,"pivot":{"x":0.0,"y":1.94000244140625,"z":3.4800000190734865},"rotation":{"x":0.19330757856369019,"y":-0.7613869309425354,"z":0.26256051659584048,"w":0.5603894591331482},"size":10.0,"orthographic":false}